celery_worker/__init__.py
celery_worker/app.py
celery_worker/plugin.py
celery_worker/settings.py
celery_worker/tasks/__init__.py
celery_worker/tasks/base.py
celery_worker/tasks/demo.py
django_celery_worker-0.0.2.dist-info/LICENSE
django_celery_worker-0.0.2.dist-info/METADATA
django_celery_worker-0.0.2.dist-info/WHEEL
django_celery_worker-0.0.2.dist-info/top_level.txt
django_celery_worker-0.0.2.dist-info/RECORD
