Metadata-Version: 2.1
Name: django-celery-worker
Version: 0.0.2
Summary: An Util for python celery worker packaging.
Home-page: UNKNOWN
Author: df_coding
Author-email: df_coding@163.com
License: UNKNOWN
Keywords: celery worker
Platform: UNKNOWN
